hermes_system_nodes/__init__.py
hermes_system_nodes/cpu_node.py
hermes_system_nodes/ping_node.py
hermes_system_nodes-1.0.1.dist-info/METADATA
hermes_system_nodes-1.0.1.dist-info/WHEEL
hermes_system_nodes-1.0.1.dist-info/entry_points.txt
hermes_system_nodes-1.0.1.dist-info/RECORD
