Metadata-Version: 2.4
Name: hermes-system-nodes
Version: 1.0.1
Summary: Nodes to capture system metrics
Author-email: floris vernieuwe <floris@vernieuwe.eu>
Requires-Python: >=3.10
Requires-Dist: node-hermes-core>=1.2.0
Requires-Dist: psutil>=7.0.0
Requires-Dist: pythonping>=1.1.4
